psl/__init__.py
psl/psl.txt
psl/py.typed
psl-2025.5.26.dist-info/LICENSE
psl-2025.5.26.dist-info/METADATA
psl-2025.5.26.dist-info/WHEEL
psl-2025.5.26.dist-info/top_level.txt
psl-2025.5.26.dist-info/RECORD
